alpyen/__init__.py
alpyen/alpyen.py
alpyen/backtesting.py
alpyen/brokerinterface.py
alpyen/cli.py
alpyen/datacontainer.py
alpyen/livetrading.py
alpyen/signal.py
alpyen/strategy.py
alpyen/utils.py
alpyen-1.2.0.dist-info/AUTHORS.rst
alpyen-1.2.0.dist-info/LICENSE
alpyen-1.2.0.dist-info/METADATA
alpyen-1.2.0.dist-info/WHEEL
alpyen-1.2.0.dist-info/entry_points.txt
alpyen-1.2.0.dist-info/top_level.txt
alpyen-1.2.0.dist-info/RECORD
