Metadata-Version: 2.1
Name: alpyen
Version: 1.2.0
Summary: Python based algo trading platform for IB.
Home-page: https://github.com/peeeffchang/alpyen
Author: P.F. Chang
Author-email: peeeffchang@gmail.com
License: GNU General Public License v3
Project-URL: Documentation, https://github.com/peeeffchang/alpyen/blob/main/README.rst
Project-URL: Source, https://github.com/peeeffchang/alpyen/
Keywords: alpyen
Platform: UNKNOWN
Classifier: Development Status :: 2 - Pre-Alpha
Classifier: Intended Audience :: Developers
Classifier: License :: OSI Approved :: GNU General Public License v3 (GPLv3)
Classifier: Natural Language :: English
Classifier: Programming Language :: Python :: 3
Classifier: Programming Language :: Python :: 3.6
Classifier: Programming Language :: Python :: 3.7
Classifier: Programming Language :: Python :: 3.8
Requires-Python: >=3.6
License-File: LICENSE
License-File: AUTHORS.rst
Requires-Dist: Click (>=7.0)
Requires-Dist: ib-insync
Requires-Dist: eventkit
Requires-Dist: pandas
Requires-Dist: asyncio
Requires-Dist: arch
Requires-Dist: numpy
Requires-Dist: gemini-python
